{
  "archive_url": "https://web.archive.org/web/20150919130626id_/http://hokusetsu-ikimono.com/link/e-des/osaka.jpeg",
  "content_length": "1546",
  "content_type": "image/jpeg",
  "downloaded_at": "2026-01-03T17:09:25Z",
  "effective_url": "https://web.archive.org/web/20150919130626id_/http://hokusetsu-ikimono.com/link/e-des/osaka.jpeg",
  "file_size": 1546,
  "original_url": "http://hokusetsu-ikimono.com/link/e-des/osaka.jpeg",
  "output_path": "link/e-des/osaka.jpeg",
  "resolved_original_url": "http://hokusetsu-ikimono.com/link/e-des/osaka.jpeg",
  "snapshot_date": "2015-09-19",
  "status": 200,
  "timestamp": "20150919130626"
}
