{
  "archive_url": "https://web.archive.org/web/20230321215019id_/http://hokusetsu-ikimono.com/iki-h/hidasansyouuo/index.htm",
  "content_length": "12311",
  "content_type": "text/html",
  "downloaded_at": "2026-01-03T13:48:16Z",
  "effective_url": "https://web.archive.org/web/20230321215019id_/http://hokusetsu-ikimono.com/iki-h/hidasansyouuo/index.htm",
  "file_size": 12311,
  "original_url": "http://hokusetsu-ikimono.com/iki-h/hidasansyouuo/index.htm",
  "output_path": "iki-h/hidasansyouuo/index.htm",
  "snapshot_date": "2023-03-21",
  "status": 200,
  "timestamp": "20230321215019"
}
