{
  "archive_url": "https://web.archive.org/web/20190618212627id_/http://hokusetsu-ikimono.com/kenkyu/rika-matome/rika-matome-rei.files/image001.gif",
  "content_length": "1182",
  "content_type": "image/gif",
  "downloaded_at": "2026-01-03T16:46:48Z",
  "effective_url": "https://web.archive.org/web/20190618212627id_/http://hokusetsu-ikimono.com/kenkyu/rika-matome/rika-matome-rei.files/image001.gif",
  "file_size": 1182,
  "original_url": "http://hokusetsu-ikimono.com/kenkyu/rika-matome/rika-matome-rei.files/image001.gif",
  "output_path": "kenkyu/rika-matome/rika-matome-rei.files/image001.gif",
  "resolved_original_url": "http://hokusetsu-ikimono.com/kenkyu/rika-matome/rika-matome-rei.files/image001.gif",
  "snapshot_date": "2019-06-18",
  "status": 200,
  "timestamp": "20190618212627"
}
