{
  "archive_url": "https://web.archive.org/web/20190619005021id_/http://hokusetsu-ikimono.com/meteorology/020526/hail04.jpeg",
  "content_length": "14185",
  "content_type": "image/jpeg",
  "downloaded_at": "2026-01-03T17:15:44Z",
  "effective_url": "https://web.archive.org/web/20190619005021id_/http://hokusetsu-ikimono.com/meteorology/020526/hail04.jpeg",
  "file_size": 14185,
  "original_url": "http://hokusetsu-ikimono.com/meteorology/020526/hail04.jpeg",
  "output_path": "meteorology/020526/hail04.jpeg",
  "resolved_original_url": "http://hokusetsu-ikimono.com/meteorology/020526/hail04.jpeg",
  "snapshot_date": "2019-06-19",
  "status": 200,
  "timestamp": "20190619005021"
}
