{
  "archive_url": "https://web.archive.org/web/20190619000242id_/http://hokusetsu-ikimono.com/butterfly/oomurasaki/110622oomurasaki-02.JPG",
  "content_length": "51731",
  "content_type": "image/jpeg",
  "downloaded_at": "2026-01-03T15:47:49Z",
  "effective_url": "https://web.archive.org/web/20190619000242id_/http://hokusetsu-ikimono.com/butterfly/oomurasaki/110622oomurasaki-02.JPG",
  "file_size": 51731,
  "original_url": "http://hokusetsu-ikimono.com/butterfly/oomurasaki/110622oomurasaki-02.JPG",
  "output_path": "butterfly/oomurasaki/110622oomurasaki-02.JPG",
  "resolved_original_url": "http://hokusetsu-ikimono.com/butterfly/oomurasaki/110622oomurasaki-02.JPG",
  "snapshot_date": "2019-06-19",
  "status": 200,
  "timestamp": "20190619000242"
}
