{
  "archive_url": "https://web.archive.org/web/20160122014852id_/http://www.hokusetsu-ikimono.com:80/siiku/but-si/ageha/seityudayo.html",
  "content_length": "4263",
  "content_type": "text/html",
  "downloaded_at": "2026-01-03T18:52:53Z",
  "effective_url": "https://web.archive.org/web/20160122014852id_/http://www.hokusetsu-ikimono.com:80/siiku/but-si/ageha/seityudayo.html",
  "file_size": 4263,
  "original_url": "http://www.hokusetsu-ikimono.com:80/siiku/but-si/ageha/seityudayo.html",
  "output_path": "siiku/but-si/ageha/seityudayo.html",
  "resolved_original_url": "http://www.hokusetsu-ikimono.com:80/siiku/but-si/ageha/seityudayo.html",
  "snapshot_date": "2016-01-22",
  "status": 200,
  "timestamp": "20160122014852"
}
