{
  "archive_url": "https://web.archive.org/web/20230603144101id_/http://hokusetsu-ikimono.com/link/joho-all/sirabe/sirabe-3.html",
  "content_length": "4494",
  "content_type": "text/html",
  "downloaded_at": "2026-01-03T17:11:43Z",
  "effective_url": "https://web.archive.org/web/20230603144101id_/http://hokusetsu-ikimono.com/link/joho-all/sirabe/sirabe-3.html",
  "file_size": 4494,
  "original_url": "http://hokusetsu-ikimono.com/link/joho-all/sirabe/sirabe-3.html",
  "output_path": "link/joho-all/sirabe/sirabe-3.html",
  "resolved_original_url": "http://hokusetsu-ikimono.com/link/joho-all/sirabe/sirabe-3.html",
  "snapshot_date": "2023-06-03",
  "status": 200,
  "timestamp": "20230603144101"
}
