{
  "archive_url": "https://web.archive.org/web/20190619012611id_/http://hokusetsu-ikimono.com/iku/asagi/asa-rinsyou.jpeg",
  "content_length": "49141",
  "content_type": "image/jpeg",
  "downloaded_at": "2026-01-03T16:22:11Z",
  "effective_url": "https://web.archive.org/web/20190619012611id_/http://hokusetsu-ikimono.com/iku/asagi/asa-rinsyou.jpeg",
  "file_size": 49141,
  "original_url": "http://hokusetsu-ikimono.com/iku/asagi/asa-rinsyou.jpeg",
  "output_path": "iku/asagi/asa-rinsyou.jpeg",
  "resolved_original_url": "http://hokusetsu-ikimono.com/iku/asagi/asa-rinsyou.jpeg",
  "snapshot_date": "2019-06-19",
  "status": 200,
  "timestamp": "20190619012611"
}
