{
  "archive_url": "https://web.archive.org/web/20190619014214id_/http://hokusetsu-ikimono.com/meteorology/051222/yuki-05.JPG",
  "content_length": "50912",
  "content_type": "image/jpeg",
  "downloaded_at": "2026-01-03T17:15:56Z",
  "effective_url": "https://web.archive.org/web/20190619014214id_/http://hokusetsu-ikimono.com/meteorology/051222/yuki-05.JPG",
  "file_size": 50912,
  "original_url": "http://hokusetsu-ikimono.com/meteorology/051222/yuki-05.JPG",
  "output_path": "meteorology/051222/yuki-05.JPG",
  "resolved_original_url": "http://hokusetsu-ikimono.com/meteorology/051222/yuki-05.JPG",
  "snapshot_date": "2019-06-19",
  "status": 200,
  "timestamp": "20190619014214"
}
