{
  "archive_url": "https://web.archive.org/web/20230331061948id_/http://hokusetsu-ikimono.com/butterfly/kichou/index.html",
  "content_length": "9462",
  "content_type": "text/html",
  "downloaded_at": "2026-01-03T14:27:52Z",
  "effective_url": "https://web.archive.org/web/20230331061948id_/http://hokusetsu-ikimono.com/butterfly/kichou/index.html",
  "file_size": 9462,
  "original_url": "http://hokusetsu-ikimono.com/butterfly/kichou/index.html",
  "output_path": "butterfly/kichou/index.html",
  "resolved_original_url": "http://hokusetsu-ikimono.com/butterfly/kichou/index.html",
  "snapshot_date": "2023-03-31",
  "status": 200,
  "timestamp": "20230331061948"
}
