{
  "archive_url": "https://web.archive.org/web/20211210090252id_/http://www.hokusetsu-ikimono.com/iki-h/batta/omagarifukibatta/index.htm",
  "content_length": "5454",
  "content_type": "text/html",
  "downloaded_at": "2026-01-03T17:55:51Z",
  "effective_url": "https://web.archive.org/web/20211210090252id_/http://www.hokusetsu-ikimono.com/iki-h/batta/omagarifukibatta/index.htm",
  "file_size": 5454,
  "original_url": "http://www.hokusetsu-ikimono.com/iki-h/batta/omagarifukibatta/index.htm",
  "output_path": "iki-h/batta/omagarifukibatta/index.htm",
  "resolved_original_url": "http://www.hokusetsu-ikimono.com/iki-h/batta/omagarifukibatta/index.htm",
  "snapshot_date": "2021-12-10",
  "status": 200,
  "timestamp": "20211210090252"
}
