{
  "archive_url": "https://web.archive.org/web/20051112003727id_/http://www.wombat.zaq.ne.jp:80/ashitaka/kousairikai/mise.html",
  "content_length": "4653",
  "content_type": "text/html",
  "downloaded_at": "2026-01-05T09:30:37Z",
  "effective_url": "https://web.archive.org/web/20051112003727id_/http://www.wombat.zaq.ne.jp:80/ashitaka/kousairikai/mise.html",
  "file_size": 4653,
  "original_url": "http://www.wombat.zaq.ne.jp:80/ashitaka/kousairikai/mise.html",
  "output_path": "ashitaka/kousairikai/mise.html",
  "resolved_original_url": "http://www.wombat.zaq.ne.jp:80/ashitaka/kousairikai/mise.html",
  "snapshot_date": "2005-11-12",
  "status": 200,
  "timestamp": "20051112003727"
}
