{
  "archive_url": "https://web.archive.org/web/20230321214927id_/http://hokusetsu-ikimono.com/in-life/oosansyouuo/index.htm",
  "content_length": "5627",
  "content_type": "text/html",
  "downloaded_at": "2026-01-03T16:37:44Z",
  "effective_url": "https://web.archive.org/web/20230321214927id_/http://hokusetsu-ikimono.com/in-life/oosansyouuo/index.htm",
  "file_size": 5627,
  "original_url": "http://hokusetsu-ikimono.com/in-life/oosansyouuo/index.htm",
  "output_path": "in-life/oosansyouuo/index.htm",
  "resolved_original_url": "http://hokusetsu-ikimono.com/in-life/oosansyouuo/index.htm",
  "snapshot_date": "2023-03-21",
  "status": 200,
  "timestamp": "20230321214927"
}
