{
  "archive_url": "https://web.archive.org/web/20040830153407id_/http://www.wombat.zaq.ne.jp:80/ashitaka/kousairikai/saigon/tea.jpeg",
  "content_length": "16366",
  "content_type": "image/jpeg",
  "downloaded_at": "2026-01-05T09:31:11Z",
  "effective_url": "https://web.archive.org/web/20040830153407id_/http://www.wombat.zaq.ne.jp:80/ashitaka/kousairikai/saigon/tea.jpeg",
  "file_size": 16366,
  "original_url": "http://www.wombat.zaq.ne.jp:80/ashitaka/kousairikai/saigon/tea.jpeg",
  "output_path": "ashitaka/kousairikai/saigon/tea.jpeg",
  "resolved_original_url": "http://www.wombat.zaq.ne.jp:80/ashitaka/kousairikai/saigon/tea.jpeg",
  "snapshot_date": "2004-08-30",
  "status": 200,
  "timestamp": "20040830153407"
}
