{
  "archive_url": "https://web.archive.org/web/20051119120103id_/http://www.wombat.zaq.ne.jp:80/ashitaka/ham/ha-B.html",
  "content_length": "652",
  "content_type": "text/html",
  "downloaded_at": "2026-01-05T08:58:45Z",
  "effective_url": "https://web.archive.org/web/20051119120103id_/http://www.wombat.zaq.ne.jp:80/ashitaka/ham/ha-B.html",
  "file_size": 652,
  "original_url": "http://www.wombat.zaq.ne.jp:80/ashitaka/ham/ha-B.html",
  "output_path": "ashitaka/ham/ha-B.html",
  "resolved_original_url": "http://www.wombat.zaq.ne.jp:80/ashitaka/ham/ha-B.html",
  "snapshot_date": "2005-11-19",
  "status": 200,
  "timestamp": "20051119120103"
}
