{
  "archive_url": "https://web.archive.org/web/20190619024842id_/http://hokusetsu-ikimono.com/butterfly/akashijimi/130604-01IMGP9575akashijimi.JPG",
  "content_length": "35024",
  "content_type": "image/jpeg",
  "downloaded_at": "2026-01-03T13:39:09Z",
  "effective_url": "https://web.archive.org/web/20190619024842id_/http://hokusetsu-ikimono.com/butterfly/akashijimi/130604-01IMGP9575akashijimi.JPG",
  "file_size": 35024,
  "original_url": "http://hokusetsu-ikimono.com/butterfly/akashijimi/130604-01IMGP9575akashijimi.JPG",
  "output_path": "butterfly/akashijimi/130604-01IMGP9575akashijimi.JPG",
  "snapshot_date": "2019-06-19",
  "status": 200,
  "timestamp": "20190619024842"
}
