{
  "archive_url": "https://web.archive.org/web/20190618232804id_/http://hokusetsu-ikimono.com/iki-h/katatumuri/160613-01-P1040626.JPG",
  "content_length": "97496",
  "content_type": "image/jpeg",
  "downloaded_at": "2026-01-03T13:51:16Z",
  "effective_url": "https://web.archive.org/web/20190618232804id_/http://hokusetsu-ikimono.com/iki-h/katatumuri/160613-01-P1040626.JPG",
  "file_size": 97496,
  "original_url": "http://hokusetsu-ikimono.com/iki-h/katatumuri/160613-01-P1040626.JPG",
  "output_path": "iki-h/katatumuri/160613-01-P1040626.JPG",
  "snapshot_date": "2019-06-18",
  "status": 200,
  "timestamp": "20190618232804"
}
