{
  "archive_url": "https://web.archive.org/web/20190618175830id_/http://hokusetsu-ikimono.com/kurasi/toriw/ILLA020.GIF",
  "content_length": "7872",
  "content_type": "image/gif",
  "downloaded_at": "2026-01-03T17:07:59Z",
  "effective_url": "https://web.archive.org/web/20190618175830id_/http://hokusetsu-ikimono.com/kurasi/toriw/ILLA020.GIF",
  "file_size": 7872,
  "original_url": "http://hokusetsu-ikimono.com/kurasi/toriw/ILLA020.GIF",
  "output_path": "kurasi/toriw/ILLA020.GIF",
  "resolved_original_url": "http://hokusetsu-ikimono.com/kurasi/toriw/ILLA020.GIF",
  "snapshot_date": "2019-06-18",
  "status": 200,
  "timestamp": "20190618175830"
}
