{
  "archive_url": "https://web.archive.org/web/20041222205341id_/http://www.wombat.zaq.ne.jp:80/ashitaka/kousairikai/Rokuyaon/ICO_276.GIF",
  "content_length": "98",
  "content_type": "image/gif",
  "downloaded_at": "2026-01-05T09:29:06Z",
  "effective_url": "https://web.archive.org/web/20041222205341id_/http://www.wombat.zaq.ne.jp:80/ashitaka/kousairikai/Rokuyaon/ICO_276.GIF",
  "file_size": 98,
  "original_url": "http://www.wombat.zaq.ne.jp:80/ashitaka/kousairikai/Rokuyaon/ICO_276.GIF",
  "output_path": "ashitaka/kousairikai/Rokuyaon/ICO_276.GIF",
  "resolved_original_url": "http://www.wombat.zaq.ne.jp:80/ashitaka/kousairikai/Rokuyaon/ICO_276.GIF",
  "snapshot_date": "2004-12-22",
  "status": 200,
  "timestamp": "20041222205341"
}
