{
  "archive_url": "https://web.archive.org/web/20230331072221id_/http://hokusetsu-ikimono.com/butterfly/misujichou/index.htm",
  "content_length": "8920",
  "content_type": "text/html",
  "downloaded_at": "2026-01-03T14:33:30Z",
  "effective_url": "https://web.archive.org/web/20230331072221id_/http://hokusetsu-ikimono.com/butterfly/misujichou/index.htm",
  "file_size": 8920,
  "original_url": "http://hokusetsu-ikimono.com/butterfly/misujichou/index.htm",
  "output_path": "butterfly/misujichou/index.htm",
  "resolved_original_url": "http://hokusetsu-ikimono.com/butterfly/misujichou/index.htm",
  "snapshot_date": "2023-03-31",
  "status": 200,
  "timestamp": "20230331072221"
}
