{
  "archive_url": "https://web.archive.org/web/20190619004104id_/http://hokusetsu-ikimono.com/iki-h/itachi/060707/itachi-007.JPG",
  "content_length": "23430",
  "content_type": "image/jpeg",
  "downloaded_at": "2026-01-03T15:24:47Z",
  "effective_url": "https://web.archive.org/web/20190619004104id_/http://hokusetsu-ikimono.com/iki-h/itachi/060707/itachi-007.JPG",
  "file_size": 23430,
  "original_url": "http://hokusetsu-ikimono.com/iki-h/itachi/060707/itachi-007.JPG",
  "output_path": "iki-h/itachi/060707/itachi-007.JPG",
  "resolved_original_url": "http://hokusetsu-ikimono.com/iki-h/itachi/060707/itachi-007.JPG",
  "snapshot_date": "2019-06-19",
  "status": 200,
  "timestamp": "20190619004104"
}
