{
  "archive_url": "https://web.archive.org/web/20240223010302id_/http://www.hokusetsu-ikimono.com/yasou/nogeshi/index.htm",
  "content_length": "3544",
  "content_type": "text/html",
  "downloaded_at": "2026-01-03T17:45:21Z",
  "effective_url": "https://web.archive.org/web/20240223010302id_/http://www.hokusetsu-ikimono.com/yasou/nogeshi/index.htm",
  "file_size": 3544,
  "original_url": "http://hokusetsu-ikimono.com/yasou/nogeshi/index.htm",
  "output_path": "yasou/nogeshi/index.htm",
  "resolved_original_url": "http://www.hokusetsu-ikimono.com/yasou/nogeshi/index.htm",
  "snapshot_date": "2024-02-23",
  "status": 200,
  "timestamp": "20240223010302"
}
