{
  "archive_url": "https://web.archive.org/web/20190619005120id_/http://hokusetsu-ikimono.com/iki-h/katatumuri/110617nipponmaimai-04.JPG",
  "content_length": "116291",
  "content_type": "image/jpeg",
  "downloaded_at": "2026-01-03T15:30:02Z",
  "effective_url": "https://web.archive.org/web/20190619005120id_/http://hokusetsu-ikimono.com/iki-h/katatumuri/110617nipponmaimai-04.JPG",
  "file_size": 116291,
  "original_url": "http://hokusetsu-ikimono.com/iki-h/katatumuri/110617nipponmaimai-04.JPG",
  "output_path": "iki-h/katatumuri/110617nipponmaimai-04.JPG",
  "resolved_original_url": "http://hokusetsu-ikimono.com/iki-h/katatumuri/110617nipponmaimai-04.JPG",
  "snapshot_date": "2019-06-19",
  "status": 200,
  "timestamp": "20190619005120"
}
