{
  "archive_url": "https://web.archive.org/web/20190618223423id_/http://hokusetsu-ikimono.com/butterfly/tsumakichou/120423tsumakichou-02.JPG",
  "content_length": null,
  "content_type": null,
  "downloaded_at": "2026-01-03T13:43:31Z",
  "effective_url": null,
  "file_size": 51217,
  "note": "metadata generated without re-downloading existing file",
  "original_url": "http://hokusetsu-ikimono.com/butterfly/tsumakichou/120423tsumakichou-02.JPG",
  "output_path": "butterfly/tsumakichou/120423tsumakichou-02.JPG",
  "snapshot_date": "2019-06-18",
  "status": null,
  "timestamp": "20190618223423"
}
