{
  "archive_url": "https://web.archive.org/web/20040504160222id_/http://www.wombat.zaq.ne.jp:80/ashitaka/litlte-B/gomi.html",
  "content_length": "6501",
  "content_type": "text/html",
  "downloaded_at": "2026-01-05T09:41:53Z",
  "effective_url": "https://web.archive.org/web/20040504160222id_/http://www.wombat.zaq.ne.jp:80/ashitaka/litlte-B/gomi.html",
  "file_size": 6501,
  "original_url": "http://www.wombat.zaq.ne.jp:80/ashitaka/litlte-B/gomi.html",
  "output_path": "ashitaka/litlte-B/gomi.html",
  "resolved_original_url": "http://www.wombat.zaq.ne.jp:80/ashitaka/litlte-B/gomi.html",
  "snapshot_date": "2004-05-04",
  "status": 200,
  "timestamp": "20040504160222"
}
