{
  "archive_url": "https://web.archive.org/web/20170103080237id_/http://www.hokusetsu-ikimono.com/iki-h/saijiki/120112zaoh/%E3%83%8A%E3%83%8A%E3%82%AB%E3%83%9E%E3%83%89%E3%81%A8%E3%82%A2%E3%83%88%E3%83%AA.JPG",
  "content_length": "119798",
  "content_type": "image/jpeg",
  "downloaded_at": "2026-01-03T18:12:42Z",
  "effective_url": "https://web.archive.org/web/20170103080237id_/http://www.hokusetsu-ikimono.com/iki-h/saijiki/120112zaoh/%E3%83%8A%E3%83%8A%E3%82%AB%E3%83%9E%E3%83%89%E3%81%A8%E3%82%A2%E3%83%88%E3%83%AA.JPG",
  "file_size": 119798,
  "original_url": "http://www.hokusetsu-ikimono.com/iki-h/saijiki/120112zaoh/%E3%83%8A%E3%83%8A%E3%82%AB%E3%83%9E%E3%83%89%E3%81%A8%E3%82%A2%E3%83%88%E3%83%AA.JPG",
  "output_path": "iki-h/saijiki/120112zaoh/%E3%83%8A%E3%83%8A%E3%82%AB%E3%83%9E%E3%83%89%E3%81%A8%E3%82%A2%E3%83%88%E3%83%AA.JPG",
  "resolved_original_url": "http://www.hokusetsu-ikimono.com/iki-h/saijiki/120112zaoh/%E3%83%8A%E3%83%8A%E3%82%AB%E3%83%9E%E3%83%89%E3%81%A8%E3%82%A2%E3%83%88%E3%83%AA.JPG",
  "snapshot_date": "2017-01-03",
  "status": 200,
  "timestamp": "20170103080237"
}
